setup.py
probability_stlc/Binomialdistribution.py
probability_stlc/Gaussiandistribution.py
probability_stlc/Generaldistribution.py
probability_stlc/__init__.py
probability_stlc.egg-info/PKG-INFO
probability_stlc.egg-info/SOURCES.txt
probability_stlc.egg-info/dependency_links.txt
probability_stlc.egg-info/not-zip-safe
probability_stlc.egg-info/top_level.txt