Metadata-Version: 2.1
Name: probability-stlc
Version: 1.0
Summary: Gaussian distributions
